nightscout_dash/__init__.py
nightscout_dash/main.py
nightscout_dash-1.6.0.dist-info/METADATA
nightscout_dash-1.6.0.dist-info/WHEEL
nightscout_dash-1.6.0.dist-info/entry_points.txt
nightscout_dash-1.6.0.dist-info/top_level.txt
nightscout_dash-1.6.0.dist-info/RECORD
