Metadata-Version: 2.4
Name: nightscout-dash
Version: 1.6.0
Summary: Web dashboard for Nightscout glucose data
Requires-Python: >=3.8
Requires-Dist: flask>=2.0.0
Requires-Dist: requests>=2.25.0
Requires-Dist: waitress>=2.0.0
